odoo10_addon_website_crm_recaptcha-10.0.1.0.0-py2.7-nspkg.pth
odoo/addons/website_crm_recaptcha/__manifest__.py
odoo/addons/website_crm_recaptcha/__init__.py
odoo/addons/website_crm_recaptcha/README.rst
odoo/addons/website_crm_recaptcha/views/website_crm_template.xml
odoo/addons/website_crm_recaptcha/data/ir_model_data.xml
odoo10_addon_website_crm_recaptcha-10.0.1.0.0.dist-info/top_level.txt
odoo10_addon_website_crm_recaptcha-10.0.1.0.0.dist-info/WHEEL
odoo10_addon_website_crm_recaptcha-10.0.1.0.0.dist-info/RECORD
odoo10_addon_website_crm_recaptcha-10.0.1.0.0.dist-info/metadata.json
odoo10_addon_website_crm_recaptcha-10.0.1.0.0.dist-info/DESCRIPTION.rst
odoo10_addon_website_crm_recaptcha-10.0.1.0.0.dist-info/METADATA
odoo10_addon_website_crm_recaptcha-10.0.1.0.0.dist-info/namespace_packages.txt
